farabi/IO.py
farabi/__init__.py
farabi/visualization.py
farabi/feature_extraction/__init__.py
farabi/preprocessing/__init__.py
farabi/preprocessing/point_operation/__init__.py
farabi/preprocessing/point_operation/gamma_correction.py
farabi/preprocessing/point_operation/logarithmic_transformations.py
farabi/segmentation/__init__.py
farabi-0.3.1.dist-info/METADATA
farabi-0.3.1.dist-info/WHEEL
farabi-0.3.1.dist-info/top_level.txt
farabi-0.3.1.dist-info/RECORD
