Metadata-Version: 2.2
Name: farabi
Version: 0.3.1
Summary: A very simple math operations library
Home-page: https://github.com/yourusername/my_simple_lib
Author: Tezeghdenti Mohamed
Author-email: mohamed.tezeghdenti@ensi-uma.tn
Classifier: Programming Language :: Python :: 3
Classifier: License :: OSI Approved :: MIT License
Classifier: Operating System :: OS Independent
Requires-Python: >=3.6
Dynamic: author
Dynamic: author-email
Dynamic: classifier
Dynamic: description-content-type
Dynamic: home-page
Dynamic: requires-python
Dynamic: summary
